README.rst
setup.py
JPMyNumber.egg-info/PKG-INFO
JPMyNumber.egg-info/SOURCES.txt
JPMyNumber.egg-info/dependency_links.txt
JPMyNumber.egg-info/top_level.txt
jpmynumber/__init__.py
jpmynumber/core.py
jpmynumber/exceptions.py
jpmynumber/individual.py
jpmynumber/legalentity.py