Metadata-Version: 1.0
Name: JPMyNumber
Version: 0.2.2
Summary: MyNumber (Japanese common number of social security and tax) library
Home-page: https://github.com/itkr/JPMyNumber
Author: itkr
Author-email: itkrst@gmail.com
License: MIT
Keywords: MyNumber,Japanese
Platform: UNKNOWN
